ejercicio4.v
//Mux 2:1

module Mux2_1(input wire D0, D1, S, output wire Y);

    assign Y = S ? D1 : D0;

endmodule

//Mux 4:1
module Mux4_1(input wire D0, D1, D2, D3, S0, S1, output wire Y);

    wire Y1, Y2;

    Mux2_1 mux0(Y1, D0, D1, S0);
    Mux2_1 mux1(Y2, D2, D3, S0);

    Mux2_1 mux3(Y, Y1, Y2, S1);

endmodule

//Mux 8:1
module Mux8_1(input wire D0, D1, D2, D3, D4, D5, D6, D7, S0, S1, S2, output wire Y);

    wire Y1, Y2;

    Mux4_1 mux0(Y1, D0, D1, D2, D3, S1, S2);
    Mux4_1 mux1(Y2, D4, D5, D6, D7, S1, S2);

    Mux2_1 mux3(Y, Y1, Y2, S0);

endmodule

//TABLA 1 MUX 8:1
module Ejercicio1_mux8(input wire A, B, C, output wire Y);

  wire HIGH, LOW;
  assign HIGH = 1;
  assign LOW = 0;

  Mux8_1 mux0(Y, LOW, HIGH, HIGH, LOW, HIGH, LOW, LOW, HIGH, A, B, C);

endmodule

ejercicio4_tb.v
module testbench();

  reg r1, r2, r3, r4, r5, r6, r7, r8, r9, r10, r11, r12, r13, r14, r15, r16, r17, r18, r19, r20, r21, r22, r23, r24, r25, r26,r27, r28;
  wire out1, out2, out3, out4, out5, out6, out7, out8;

  Ejercicio1_mux8 mux0(r1, r2, r3, out1);

  initial begin
    $display(" tabla 1 - mux 8:1");
    $display("A B C | Y");
    $display("------|---");
    $monitor("%b %b %b | %b ", r1, r2, r3, out1);
    r1 = 0; r2 = 0; r3=0;
    #1 r3 = 1;
    #1 r2 = 1; r3 = 0;
    #1 r3 = 1;
    #1 r1 = 1; r2 = 0; r3 = 0;
    #1 r3 = 1;
    #1 r2 = 1; r3 = 0;
    #1 r3 = 1;
  end


  initial
    #10 $finish;

  initial begin
    $dumpfile("ejercicio4_tb.vcd");
    $dumpvars(0, testbench);
  end

endmodule

ejercicio4_tb.vcd
$date
	Sat Aug 15 16:53:11 2020
$end
$version
	Icarus Verilog
$end
$timescale
	1ps
$end
$scope module testbench $end
$var wire 1 ! out1 $end
$var reg 1 " r1 $end
$var reg 1 # r2 $end
$var reg 1 $ r3 $end
$scope module mux0 $end
$var wire 1 % A $end
$var wire 1 # B $end
$var wire 1 $ C $end
$var wire 1 & HIGH $end
$var wire 1 ' LOW $end
$var wire 1 ! Y $end
$scope module mux0 $end
$var wire 1 ! D0 $end
$var wire 1 ' D1 $end
$var wire 1 & D2 $end
$var wire 1 & D3 $end
$var wire 1 ' D4 $end
$var wire 1 & D5 $end
$var wire 1 ' D6 $end
$var wire 1 ' D7 $end
$var wire 1 & S0 $end
$var wire 1 % S1 $end
$var wire 1 # S2 $end
$var wire 1 $ Y $end
$var wire 1 ( Y1 $end
$var wire 1 ) Y2 $end
$scope module mux0 $end
$var wire 1 ( D0 $end
$var wire 1 ! D1 $end
$var wire 1 ' D2 $end
$var wire 1 & D3 $end
$var wire 1 & S0 $end
$var wire 1 % S1 $end
$var wire 1 # Y $end
$var wire 1 * Y1 $end
$var wire 1 + Y2 $end
$scope module mux0 $end
$var wire 1 * D0 $end
$var wire 1 ( D1 $end
$var wire 1 ! S $end
$var wire 1 & Y $end
$upscope $end
$scope module mux1 $end
$var wire 1 + D0 $end
$var wire 1 ' D1 $end
$var wire 1 & S $end
$var wire 1 & Y $end
$upscope $end
$scope module mux3 $end
$var wire 1 # D0 $end
$var wire 1 * D1 $end
$var wire 1 + S $end
$var wire 1 % Y $end
$upscope $end
$upscope $end
$scope module mux1 $end
$var wire 1 ) D0 $end
$var wire 1 ' D1 $end
$var wire 1 & D2 $end
$var wire 1 ' D3 $end
$var wire 1 ' S0 $end
$var wire 1 % S1 $end
$var wire 1 # Y $end
$var wire 1 , Y1 $end
$var wire 1 - Y2 $end
$scope module mux0 $end
$var wire 1 , D0 $end
$var wire 1 ) D1 $end
$var wire 1 ' S $end
$var wire 1 ' Y $end
$upscope $end
$scope module mux1 $end
$var wire 1 - D0 $end
$var wire 1 & D1 $end
$var wire 1 ' S $end
$var wire 1 ' Y $end
$upscope $end
$scope module mux3 $end
$var wire 1 # D0 $end
$var wire 1 , D1 $end
$var wire 1 - S $end
$var wire 1 % Y $end
$upscope $end
$upscope $end
$scope module mux3 $end
$var wire 1 $ D0 $end
$var wire 1 ( D1 $end
$var wire 1 ) S $end
$var wire 1 & Y $end
$upscope $end
$upscope $end
$upscope $end
$upscope $end
$enddefinitions $end
#0
$dumpvars
z-
z,
z+
z*
z)
z(
x'
x&
x%
0$
0#
0"
z!
$end
#1
1$
#2
0$
1#
#3
1$
#4
0$
0#
1"
#5
1$
#6
0$
1#
#7
1$
